qai/schema/__init__.py
qai/schema/extensions.py
qai/schema/mergers/company_merger.py
qai/schema/mergers/merge.py
qai/schema/models/__init__.py
qai/schema/models/addons.py
qai/schema/models/address_model.py
qai/schema/models/campaign_model.py
qai/schema/models/company_model.py
qai/schema/models/contact_model.py
qai/schema/models/email_model.py
qai/schema/models/existing_customer_model.py
qai/schema/models/job_model.py
qai/schema/models/models.py
qai/schema/models/name_model.py
qai/schema/models/person_model.py
qai/schema/models/phone_number_model.py
qai/schema/models/qbeanie.py
qai/schema/models/social_media_model.py
qai/schema/parsers/__init__.py
qai/schema/parsers/address_parser_postal.py
qai/schema/parsers/address_parser_pyap.py
qai/schema/py.typed
qai/schema/resolvers/__init__.py
qai/schema/resolvers/person_resolver.py
qai/schema/utils/utils.py
qai_schema-0.6.2.2.dist-info/METADATA
qai_schema-0.6.2.2.dist-info/WHEEL
qai_schema-0.6.2.2.dist-info/RECORD
