Metadata-Version: 2.1
Name: qai-schema
Version: 0.6.2.2
Summary: 
Author: parnell
Author-email: 3028114+parnell@users.noreply.github.com
Requires-Python: >=3.11,<4.0
Classifier: Programming Language :: Python :: 3
Classifier: Programming Language :: Python :: 3.11
Classifier: Programming Language :: Python :: 3.12
Requires-Dist: addressformatting (>=1.3.2,<2.0.0)
Requires-Dist: beanie (>=1.26.0,<2.0.0)
Requires-Dist: flexible-datetime (>=0.3.2,<0.4.0)
Requires-Dist: nameparser (>=1.1.3,<2.0.0)
Requires-Dist: phonenumbers (>=8.13.39,<9.0.0)
Requires-Dist: pi-conf (>=0.8.5.1,<0.9.0.0)
Requires-Dist: pyap (>=0.3.1,<0.4.0)
Requires-Dist: pycountry (>=24.6.1,<25.0.0)
Requires-Dist: pydantic-settings (>=2.3.4,<3.0.0)
Requires-Dist: pydantic[email] (>=2.7.4,<3.0.0)
